{
  "auth": "zef::tbrowder",
  "authors": [
    "Tom Browder"
  ],
  "build-depends": [
  ],
  "depends": [
    "Date::Names",
    "Text::Utils",
    "CSV::Parser"
  ],
  "description": "Provides class data for producing calendars",
  "license": "Artistic-2.0",
  "name": "Calendar",
  "perl": "6.d",
  "provides": {
    "Calendar": "lib/Calendar.rakumod"
  },
  "resources": [
  ],
  "source-url": "https://github.com/tbrowder/Calendar.git",
  "tags": [
  ],
  "test-depends": [
    "Test::Output"
  ],
  "version": "0.0.1"
}
